{
	"credit": "Made with Blockbench",
	"parent": "block/block",
	"textures": {
		"particle": "eki:blocks/handrail",
		"color1": "eki:blocks/handrail"
	},
	"elements": [
		{
			"from": [15.5, 0, 0],
			"to": [16, 16, 1.5],
			"rotation": {"angle": 0, "axis": "y", "origin": [23.5, 8, 8]},
			"faces": {
				"north": {"uv": [0, 4, 2, 16], "texture": "#color1"},
				"east": {"uv": [0, 4, 2, 16], "texture": "#color1"},
				"south": {"uv": [0, 4, 2, 16], "texture": "#color1"},
				"west": {"uv": [0, 4, 2, 16], "texture": "#color1"},
				"up": {"uv": [0, 4, 2, 16], "texture": "#color1"},
				"down": {"uv": [0, 4, 2, 16], "texture": "#color1"}
			}
		},
		{
			"from": [0, 0, 0],
			"to": [0.5, 16, 1.5],
			"faces": {
				"north": {"uv": [0, 4, 1, 16], "texture": "#color1"},
				"east": {"uv": [0, 4, 1, 16], "texture": "#color1"},
				"south": {"uv": [0, 4, 1, 16], "texture": "#color1"},
				"west": {"uv": [0, 4, 1, 16], "texture": "#color1"},
				"up": {"uv": [0, 4, 1, 16], "texture": "#color1"},
				"down": {"uv": [0, 4, 1, 16], "texture": "#color1"}
			}
		},
		{
			"from": [15.5, 9.82957, 2.4525],
			"to": [16, 12.82957, 3.9525],
			"rotation": {"angle": 22.5, "axis": "x", "origin": [23.5, 17.82957, 10.4525]},
			"faces": {
				"north": {"uv": [0, 0, 1, 1], "texture": "#color1"},
				"east": {"uv": [0, 0, 0.5, 0.5], "texture": "#color1"},
				"south": {"uv": [0, 0, 0.5, 0.5], "texture": "#color1"},
				"west": {"uv": [0, 0, 0.5, 0.5], "texture": "#color1"},
				"up": {"uv": [0, 0, 0.5, 0.5], "texture": "#color1"},
				"down": {"uv": [0, 0, 0.5, 0.5], "texture": "#color1"}
			}
		},
		{
			"from": [0, 9.82957, 2.4525],
			"to": [0.5, 12.82957, 3.9525],
			"rotation": {"angle": 22.5, "axis": "x", "origin": [8, 17.82957, 10.4525]},
			"faces": {
				"north": {"uv": [0, 0, 1, 1], "texture": "#color1"},
				"east": {"uv": [0, 0, 0.5, 0.5], "texture": "#color1"},
				"south": {"uv": [0, 0, 0.5, 0.5], "texture": "#color1"},
				"west": {"uv": [0, 0, 0.5, 0.5], "texture": "#color1"},
				"up": {"uv": [0, 0, 0.5, 0.5], "texture": "#color1"},
				"down": {"uv": [0, 0, 0.5, 0.5], "texture": "#color1"}
			}
		},
		{
			"from": [15.5, 15.52164, 1.74805],
			"to": [16, 17.67164, 3.14805],
			"rotation": {"angle": 0, "axis": "y", "origin": [23.5, 23.77164, 9.64805]},
			"faces": {
				"north": {"uv": [0, 0, 1, 1], "texture": "#color1"},
				"east": {"uv": [0, 0, 0.5, 0.5], "texture": "#color1"},
				"south": {"uv": [0, 0, 0.5, 0.5], "texture": "#color1"},
				"west": {"uv": [0, 0, 0.5, 0.5], "texture": "#color1"},
				"up": {"uv": [0, 0, 0.5, 0.5], "texture": "#color1"},
				"down": {"uv": [0, 0, 0.5, 0.5], "texture": "#color1"}
			}
		},
		{
			"from": [0, 15.52164, 1.74805],
			"to": [0.5, 17.67164, 3.14805],
			"rotation": {"angle": 0, "axis": "y", "origin": [8, 23.77164, 9.64805]},
			"faces": {
				"north": {"uv": [0, 0, 1, 1], "texture": "#color1"},
				"east": {"uv": [0, 0, 0.5, 0.5], "texture": "#color1"},
				"south": {"uv": [0, 0, 0.5, 0.5], "texture": "#color1"},
				"west": {"uv": [0, 0, 0.5, 0.5], "texture": "#color1"},
				"up": {"uv": [0, 0, 0.5, 0.5], "texture": "#color1"},
				"down": {"uv": [0, 0, 0.5, 0.5], "texture": "#color1"}
			}
		},
		{
			"from": [15.5, 15.77164, 1.39805],
			"to": [16, 17.27164, 3.49805],
			"rotation": {"angle": 0, "axis": "y", "origin": [23.5, 23.77164, 9.64805]},
			"faces": {
				"north": {"uv": [0, 0, 1, 1], "texture": "#color1"},
				"east": {"uv": [0, 0, 0.5, 0.5], "texture": "#color1"},
				"south": {"uv": [0, 0, 0.5, 0.5], "texture": "#color1"},
				"west": {"uv": [0, 0, 0.5, 0.5], "texture": "#color1"},
				"up": {"uv": [0, 0, 0.5, 0.5], "texture": "#color1"},
				"down": {"uv": [0, 0, 0.5, 0.5], "texture": "#color1"}
			}
		},
		{
			"from": [0, 15.77164, 1.39805],
			"to": [0.5, 17.27164, 3.49805],
			"rotation": {"angle": 0, "axis": "y", "origin": [8, 23.77164, 9.64805]},
			"faces": {
				"north": {"uv": [0, 0, 1, 1], "texture": "#color1"},
				"east": {"uv": [0, 0, 0.5, 0.5], "texture": "#color1"},
				"south": {"uv": [0, 0, 0.5, 0.5], "texture": "#color1"},
				"west": {"uv": [0, 0, 0.5, 0.5], "texture": "#color1"},
				"up": {"uv": [0, 0, 0.5, 0.5], "texture": "#color1"},
				"down": {"uv": [0, 0, 0.5, 0.5], "texture": "#color1"}
			}
		},
		{
			"from": [0.5, 15.75, 2.1],
			"to": [15.5, 17.4, 2.75],
			"rotation": {"angle": 0, "axis": "y", "origin": [8.5, 24.5, 10]},
			"faces": {
				"north": {"uv": [0, 1, 15, 3], "texture": "#color1"},
				"east": {"uv": [0, 0, 0.65, 1.65], "texture": "#color1"},
				"south": {"uv": [0, 1, 15, 3], "texture": "#color1"},
				"west": {"uv": [0, 0, 0.65, 1.65], "texture": "#color1"},
				"up": {"uv": [0, 1, 15, 2], "texture": "#color1"},
				"down": {"uv": [0, 2, 15, 3], "texture": "#color1"}
			}
		},
		{
			"from": [0.5, 16, 1.85],
			"to": [15.5, 17.25, 3.1],
			"rotation": {"angle": 0, "axis": "y", "origin": [8.5, 24.5, 10]},
			"faces": {
				"north": {"uv": [0, 1, 15, 2], "texture": "#color1"},
				"east": {"uv": [0, 0, 1.25, 1.25], "texture": "#color1"},
				"south": {"uv": [0, 1, 15, 2], "texture": "#color1"},
				"west": {"uv": [0, 0, 1.25, 1.25], "texture": "#color1"},
				"up": {"uv": [0, 1, 15, 2], "texture": "#color1"},
				"down": {"uv": [0, 1, 15, 2], "texture": "#color1"}
			}
		},
		{
			"from": [0.5, 16.25, 1.6],
			"to": [15.5, 16.9, 3.25],
			"rotation": {"angle": 0, "axis": "y", "origin": [8.5, 24.5, 10]},
			"faces": {
				"north": {"uv": [0, 2, 15, 3], "texture": "#color1"},
				"east": {"uv": [0, 0, 1.65, 0.65], "texture": "#color1"},
				"south": {"uv": [0, 1, 15, 2], "texture": "#color1"},
				"west": {"uv": [0, 0, 1.65, 0.65], "texture": "#color1"},
				"up": {"uv": [0, 1, 15, 3], "texture": "#color1"},
				"down": {"uv": [0, 0, 15, 1.65], "texture": "#color1"}
			}
		},
		{
			"from": [0.5, 0, 0],
			"to": [15.5, 0.5, 1.5],
			"faces": {
				"north": {"uv": [0, 5, 16, 7], "texture": "#color1"},
				"east": {"uv": [0, 5, 16, 7], "texture": "#color1"},
				"south": {"uv": [0, 5, 16, 7], "texture": "#color1"},
				"west": {"uv": [0, 5, 16, 7], "texture": "#color1"},
				"up": {"uv": [0, 5, 16, 7], "texture": "#color1"},
				"down": {"uv": [0, 5, 16, 7], "texture": "#color1"}
			}
		},
		{
			"from": [0.5, 3.9, 0.4],
			"to": [15.5, 4.6, 1.1],
			"rotation": {"angle": 0, "axis": "y", "origin": [8.5, 12, 8.5]},
			"faces": {
				"north": {"uv": [0, 0, 15, 0.7], "texture": "#color1"},
				"east": {"uv": [0, 0, 0.7, 0.7], "texture": "#color1"},
				"south": {"uv": [0, 0, 15, 0.7], "texture": "#color1"},
				"west": {"uv": [0, 0, 0.7, 0.7], "texture": "#color1"},
				"up": {"uv": [0, 0, 15, 0.7], "texture": "#color1"},
				"down": {"uv": [0, 0, 15, 0.7], "texture": "#color1"}
			}
		},
		{
			"from": [0.5, 7.9, 0.4],
			"to": [15.5, 8.6, 1.1],
			"rotation": {"angle": 0, "axis": "y", "origin": [8.5, 16, 8.5]},
			"faces": {
				"north": {"uv": [0, 0, 15, 0.7], "texture": "#color1"},
				"east": {"uv": [0, 0, 0.7, 0.7], "texture": "#color1"},
				"south": {"uv": [0, 0, 15, 0.7], "texture": "#color1"},
				"west": {"uv": [0, 0, 0.7, 0.7], "texture": "#color1"},
				"up": {"uv": [0, 0, 15, 0.7], "texture": "#color1"},
				"down": {"uv": [0, 0, 15, 0.7], "texture": "#color1"}
			}
		},
		{
			"from": [0.5, 11.9, 0.4],
			"to": [15.5, 12.6, 1.1],
			"rotation": {"angle": 0, "axis": "y", "origin": [8.5, 20, 8.5]},
			"faces": {
				"north": {"uv": [0, 0, 15, 0.7], "texture": "#color1"},
				"east": {"uv": [0, 0, 0.7, 0.7], "texture": "#color1"},
				"south": {"uv": [0, 0, 15, 0.7], "texture": "#color1"},
				"west": {"uv": [0, 0, 0.7, 0.7], "texture": "#color1"},
				"up": {"uv": [0, 0, 15, 0.7], "texture": "#color1"},
				"down": {"uv": [0, 0, 15, 0.7], "texture": "#color1"}
			}
		}
	],
	"display": {
		"thirdperson_righthand": {
			"rotation": [75, 315, 0],
			"translation": [0, 2.5, 0],
			"scale": [0.375, 0.375, 0.375]
		},
		"firstperson_righthand": {
			"rotation": [0, 315, 0],
			"translation": [0, 2.5, 0],
			"scale": [0.4, 0.4, 0.4]
		},
		"ground": {
			"translation": [0, 3, 0],
			"scale": [0.25, 0.25, 0.25]
		},
		"gui": {
			"rotation": [30, 45, 0],
			"scale": [0.625, 0.625, 0.625]
		},
		"head": {
			"rotation": [0, 180, 0]
		},
		"fixed": {
			"rotation": [0, 180, 0]
		}
	},
	"groups": [
		{
			"name": "group",
			"origin": [8, 8, 8],
			"children": [0, 1, 2, 3, 4, 5, 6, 7, 8, 9, 10, 11, 12, 13, 14]
		}
	]
}